api_diagnostic_tool/__init__.py
api_diagnostic_tool/cli.py
api_diagnostic_tool/dns_checker.py
api_diagnostic_tool/http_checker.py
api_diagnostic_tool/ssl_checker.py
api_diagnostic_tool-1.0.2.dist-info/METADATA
api_diagnostic_tool-1.0.2.dist-info/WHEEL
api_diagnostic_tool-1.0.2.dist-info/entry_points.txt
api_diagnostic_tool-1.0.2.dist-info/top_level.txt
api_diagnostic_tool-1.0.2.dist-info/RECORD
